jsonofabitch/__init__.py
jsonofabitch/jsob.py
jsonofabitch/jsonofabitch.lark
jsonofabitch/jsonofabitch.py
jsonofabitch-0.4.0.dist-info/METADATA
jsonofabitch-0.4.0.dist-info/WHEEL
jsonofabitch-0.4.0.dist-info/top_level.txt
jsonofabitch-0.4.0.dist-info/RECORD
