Metadata-Version: 2.1
Name: jsonofabitch
Version: 0.4.0
Summary: JSOB: Fault tolerant JSON parser. A standardization of low standards. Be a JSLOB.
Home-page: https://github.com/cmark0v/jsonofabitch/
Download-URL: 
Author: cmark0v
Author-email: c mark0v <cmark0v@protonmail.com>
License: MIT
Project-URL: Homepage, https://github.com/cmark0v/jsonofabitch/
Keywords: json,parser,linter,autocorrect,formatter,jslob,user input
Classifier: Development Status :: 4 - Beta
Classifier: Intended Audience :: Developers
Classifier: Topic :: File Formats :: JSON
Classifier: Topic :: Software Development :: Pre-processors
Classifier: Topic :: File Formats
Requires-Python: >=3.6
